flag.v
module flag(
    input clk,
    input reset_n,
    input secure,
    input risk,
    output Win,
    output Loss
);
parameter S0=3'b000,
          S1=3'b001,
          S2=3'b011,
          S3=3'b010,
          S4=3'b110;
reg [2:0] state, next_state;
always @(posedge clk or negedge reset_n) begin
    if (!reset_n)
        state <= S0;
    else
        state <= next_state;
end
always@(*) begin
    case(state)
    S0:begin 
        if(secure) next_state=S1;
        else if(risk) next_state=S4;
        else next_state=S0;
    end
    S1: begin
        if(secure) next_state=S1;
        else if(risk) next_state=S2;
        else next_state=S4;
    end
    S2: begin 
        if(secure || risk) next_state=S3;
        else next_state=S4;
    end 
    S3: begin
        if(secure) next_state=S0;
        else next_state=S4;
    end
    S4: begin 
        if(secure || risk) next_state=S4;
        else next_state=S0;
    end
    default: next_state=S0;
    endcase
end
assign Win=(state==S0&&secure==1'b1)?1'b1:1'b0;
assign Loss=(state==S4)?1'b1:1'b0;
endmodule

flag_tb.v
`timescale 1ns/1ps

module flag_tb;

    // Testbench signals
    reg  clk;
    reg  reset_n;
    reg  secure;   // S
    reg  risk;     // R
    wire Win;
    wire Loss;

    // DUT instantiation
    flag dut (
        .clk    (clk),
        .reset_n(reset_n),
        .secure (secure),
        .risk   (risk),
        .Win    (Win),
        .Loss   (Loss)
    );

    // Clock generation: 10 ns period
    initial clk = 0;
    always #5 clk = ~clk;

    // Task to apply one move (R,S) for one clock cycle
    task move;
        input r;
        input s;
        begin
            risk   = r;
            secure = s;
            @(posedge clk);  // wait for state to update
            #5; // small delay after edge for stable outputs
            $display("T=%0t  R=%b S=%b  Win=%b Loss=%b", $time, risk, secure, Win, Loss);
        end
    endtask

    initial begin
        // Open a dump file for GTKWave or similar
        $dumpfile("flag_tb.vcd");
        $dumpvars(0, flag_tb);

        // Initial values
        secure  = 0;
        risk    = 0;
        reset_n = 0;

        // Reset
        @(posedge clk);
        reset_n = 1;  // release reset at a clock edge
        @(posedge clk);
        $display("=== Start of simulation ===");

        // ------------------------------
        // TEST 1: WIN SEQUENCE
        // S0 -> S1 -> S2 -> S3 -> S0 (Win)
        // ------------------------------
        $display("\n--- TEST 1: Valid WIN path ---");

        // At BASE (S0), Stall
        move(0,0); // stay S0

        // S0 -> S1 via Secure
        move(0,1); // secure

        // Hold in S1 with secure
        move(0,1); // still S1

        // S1 -> S2 via Risk
        move(1,0); // risk

        // S2 -> S3 via any move (choose secure)
        move(0,1);

        // S3 -> S0 via Secure (this should assert Win=1 for this cycle)
        move(0,1);

        // ------------------------------
        // TEST 2: Immediate LOSS from base by Risk
        // ------------------------------
        $display("\n--- TEST 2: Risk from BASE -> LOST ---");
        // back at S0 after previous test; do Risk
        move(1,0); // should go to S4 (Loss=1)

        // Stall to reset from LOST back to BASE
        move(0,0); // S4 -> S0

        // ------------------------------
        // TEST 3: Stall in ZONE_A -> LOST
        // ------------------------------
        $display("\n--- TEST 3: Stall in ZONE_A -> LOST ---");

        // S0 -> S1 via Secure
        move(0,1);

        // Stall in S1: should go to S4 (Loss=1)
        move(0,0);

        // Stall again to reset S4 -> S0
        move(0,0);

        // ------------------------------
        // TEST 4: Risk with FLAG (S3) -> LOST
        // ------------------------------
        $display("\n--- TEST 4: Risk in FLAGGED -> LOST ---");

        // S0 -> S1 (secure)
        move(0,1);
        // S1 -> S2 (risk)
        move(1,0);
        // S2 -> S3 (any, choose risk this time)
        move(1,0);
        // In S3 now, choose risk again => LOST
        move(1,0);

        // Finish
        $display("\n=== End of simulation ===");
        #20;
        $finish;
    end

endmodule

flag_tb.vcd
$date
	Mon Dec 01 14:40:06 2025
$end
$version
	Icarus Verilog
$end
$timescale
	1ps
$end
$scope module flag_tb $end
$var wire 1 ! Win $end
$var wire 1 " Loss $end
$var reg 1 # clk $end
$var reg 1 $ reset_n $end
$var reg 1 % risk $end
$var reg 1 & secure $end
$scope module dut $end
$var wire 1 # clk $end
$var wire 1 $ reset_n $end
$var wire 1 % risk $end
$var wire 1 & secure $end
$var wire 1 ! Win $end
$var wire 1 " Loss $end
$var parameter 3 ' S0 $end
$var parameter 3 ( S1 $end
$var parameter 3 ) S2 $end
$var parameter 3 * S3 $end
$var parameter 3 + S4 $end
$var reg 3 , next_state [2:0] $end
$var reg 3 - state [2:0] $end
$upscope $end
$scope task move $end
$var reg 1 . r $end
$var reg 1 / s $end
$upscope $end
$upscope $end
$enddefinitions $end
$comment Show the parameter values. $end
$dumpall
b110 +
b10 *
b11 )
b1 (
b0 '
$end
#0
$dumpvars
x/
x.
b0 -
b0 ,
0&
0%
0$
0#
0"
0!
$end
#5000
1$
1#
#10000
0#
#15000
0/
0.
1#
#20000
0#
#25000
1#
#30000
1!
b1 ,
1&
1/
0#
#35000
0!
b1 -
1#
#40000
0#
#45000
1#
#50000
b11 ,
0&
1%
0/
1.
0#
#55000
b10 ,
b11 -
1#
#60000
1&
0%
1/
0.
0#
#65000
b0 ,
b10 -
1#
#70000
0#
#75000
1!
b1 ,
b0 -
1#
#80000
0!
b110 ,
0&
1%
0/
1.
0#
#85000
1"
b110 -
1#
#90000
b0 ,
0%
0.
0#
#95000
0"
b0 -
1#
#100000
1!
b1 ,
1&
1/
0#
#105000
0!
b1 -
1#
#110000
b110 ,
0&
0/
0#
#115000
b0 ,
1"
b110 -
1#
#120000
0#
#125000
0"
b0 -
1#
#130000
1!
b1 ,
1&
1/
0#
#135000
0!
b1 -
1#
#140000
b11 ,
0&
1%
0/
1.
0#
#145000
b10 ,
b11 -
1#
#150000
0#
#155000
b110 ,
b10 -
1#
#160000
0#
#165000
1"
b110 -
1#
